{
  "policies": {
    "BlockAboutAddons": true,
    "BlockAboutConfig": true,
    "DisplayBookmarksToolbar": true,
    "DisableFirefoxStudies": true,
    "DisableForgetButton": true,
    "DisablePocket": true,
    "DisableSystemAddonUpdate": true,
    "DisableTelemetry": true,
    "DontCheckDefaultBrowser": true,
    "FlashPlugin": {
      "Default": false,
      "Locked": true
    },
    "WebsiteFilter": {
      "Block": [
"*://www.google.com/doodles/*",
"*://*.coolmath-games.com/*",
"*://*.coolmathgames.com/*",
"*://*.coolmath.com/*",
"*://*.coolmathin.com/*",
"*://*.coolermathgames.com/*",
"*://*.hotspotshield.com/*",
"https://quickdraw.withgoogle.com/*",
"https://www.google.com/doodles/*",
"https://www.facebook.com/*",
"*://*.coursehero.com/*",
"*://*.agariov.org/*",
"*://agar.one/*",
"*://warin.space/*",
"*://*.cardsagainsthumanity.com/*",
"*://gota.io/*",
"*://www.chess.com/*",
"*://twitch.tv/*",
"*://*.aarp.com/*",
"*://flappybird.io/*",
"*://spaceone.io/*",
"*://worldsbiggestpacman.com/*",
"*://splix.io/*",
"*://www.koalastothemax.com/*",
"*://soundcloud.com/*",
"*://chess.org//*",
"*://www.laughfactory.com//*",
"*://ninjakiwi.com//*",
"*://www.adobe.com//*",
"*://moomoo.io//*",
"*://krunker.io//*"


]
    },
    "Homepage": {
      "URL": "https://www.smore.com/nfbw3-computer-science-1-01-14-2018",
      "Locked": true
    },
    "InstallAddonsPermission": {
      "Default": false
    }
  }
}
